Metadata-Version: 2.1
Name: python-aioweb
Version: 0.0.1
Summary: A barebones asyncio http library.
Home-page: https://github.com/wybiral
Author: Davy Wybiral
Author-email: davy.wybiral@gmail.com
License: MIT
Platform: UNKNOWN
Classifier: Programming Language :: Python :: 3
Classifier: License :: OSI Approved :: MIT License
Classifier: Operating System :: OS Independent
